qdown/__init__.py
qdown/qdown.py
z_examples/__init__.py
z_examples/example.py
qdown-1.1.0.dist-info/METADATA
qdown-1.1.0.dist-info/WHEEL
qdown-1.1.0.dist-info/entry_points.txt
qdown-1.1.0.dist-info/top_level.txt
qdown-1.1.0.dist-info/RECORD
