Metadata-Version: 2.1
Name: qdown
Version: 1.1.0
Summary: Client for QualitegDrive
Home-page: https://github.com/qualiteg/qdown
Author: Qualiteg Inc.
Author-email: qualiteger@qualiteg.com
Classifier: Development Status :: 3 - Alpha
Classifier: Intended Audience :: Developers
Classifier: License :: OSI Approved :: MIT License
Classifier: Programming Language :: Python :: 3
Classifier: Programming Language :: Python :: 3.7
Classifier: Programming Language :: Python :: 3.8
Classifier: Programming Language :: Python :: 3.9
Classifier: Programming Language :: Python :: 3.10
Requires-Python: >=3.7
Requires-Dist: httpx (>=0.23.0)
Requires-Dist: tqdm (>=4.64.0)
